[
    {
        "lngLat": [-0.006427, 51.543343],
        "name": "T4 Westfield Stratford",
        "address": "https://maps.app.goo.gl/7aoV4gxnoxDmim5G7",
        "lastVisited": "not sure",
        "comments": ""
    },
    {
        "lngLat": [-0.218414, 51.505633],
        "name": "T4 Westfield Shepherd's Bush",
        "address": "https://maps.app.goo.gl/4Uf7QxaCZVHd93CE7",
        "lastVisited": "not sure",
        "comments": ""
    },
    {
        "lngLat": [-0.575242, 51.237938],
        "name": "T4 Guildford",
        "address": "https://maps.app.goo.gl/wpBfLtKq2xhoRGKj7",
        "lastVisited": "",
        "comments": ""
    },
    {
        "lngLat": [-1.510919, 52.408492],
        "name": "T4 Coventry",
        "address": "https://maps.app.goo.gl/S6egdCpKhzvGD8g29",
        "lastVisited": "2025-09-08",
        "comments": "Was in Coventry for RSECon 2025..."
    },
    {
        "lngLat": [-2.588328, 51.458154],
        "name": "T4 Bristol",
        "address": "https://maps.app.goo.gl/RWHmv2JzgjdWBp1M9",
        "lastVisited": "",
        "comments": ""
    },
    {
        "lngLat": [-0.016489, 51.505508],
        "name": "T4 Canary Wharf",
        "address": "https://maps.app.goo.gl/AVcqEWAKoSneQCNS6",
        "lastVisited": "",
        "comments": ""
    },
    {
        "lngLat": [-1.083586, 53.958865],
        "name": "T4 York",
        "address": "https://maps.app.goo.gl/M24wPYrpjpmzNhVY6",
        "lastVisited": "",
        "comments": ""
    },
    {
        "lngLat": [0.9005544, 51.887303],
        "name": "T4 Colchester",
        "address": "https://maps.app.goo.gl/BQnBqvmegTEMMF469",
        "lastVisited": "",
        "comments": ""
    },
    {
        "lngLat": [-0.078578, 51.518856],
        "name": "T4 Liverpool Street",
        "address": "https://maps.app.goo.gl/fdtoNBWtLR7dqyWf8",
        "lastVisited": "2026-04-23",
        "comments": "I think I might be visiting this one a lot..."
    },
    {
        "lngLat": [-0.102056, 51.376586],
        "name": "T4 Croydon",
        "address": "https://maps.app.goo.gl/Kj3DfuFPFvRuh1ja7",
        "lastVisited": "",
        "comments": ""
    },
    {
        "lngLat": [-0.27999, 51.560233],
        "name": "T4 Wembley Park",
        "address": "https://maps.app.goo.gl/W5GwYovAEZqo1wVZ8",
        "lastVisited": "",
        "comments": ""
    },
    {
        "lngLat": [-0.14337, 50.824241],
        "name": "T4 Brighton",
        "address": "https://maps.app.goo.gl/fB1oiLViZzNBtig66",
        "lastVisited": "",
        "comments": ""
    },
    {
        "lngLat": [-0.301406, 51.41239],
        "name": "T4 Kingston",
        "address": "https://maps.app.goo.gl/8DXjBZf85VLCz72P9",
        "lastVisited": "",
        "comments": ""
    },
    {
        "lngLat": [-0.206300, 51.517363],
        "name": "T4 Notting Hill",
        "address": "https://maps.app.goo.gl/Jjjm6qo3unj9KqfV9",
        "lastVisited": "",
        "comments": ""
    },
    {
        "lngLat": [-0.304973, 51.512913],
        "name": "T4 Ealing",
        "address": "https://maps.app.goo.gl/E2ZSXnGUR35UeYVh7",
        "lastVisited": "2025-02-20",
        "comments": ""
    },
    {
        "lngLat": [-0.170828, 51.518469],
        "name": "T4 Paddington",
        "address": "https://maps.app.goo.gl/K62CuKWaLP51Njus6",
        "lastVisited": "many times but can't remember",
        "comments": "Used to be the 'local' T4 when commuting from Oxford..."
    },
    {
        "lngLat": [-0.142888, 51.538741],
        "name": "T4 Camden Town",
        "address": "https://maps.app.goo.gl/CBMr9CZo1py3HuVU8",
        "lastVisited": "",
        "comments": ""
    },
    {
        "lngLat": [0.0281831, 51.5002205],
        "name": "T4 Royal Wharf",
        "address": "https://maps.app.goo.gl/fbWMw6gvBmcHjTqi8",
        "lastVisited": "",
        "comments": ""
    },
    {
        "lngLat": [-0.1939978, 51.3647016],
        "name": "T4 Sutton",
        "address": "https://maps.app.goo.gl/eauhqLoKeUjp1wMT6",
        "lastVisited": "",
        "comments": ""
    },
    {
        "lngLat": [0.12014, 52.206762],
        "name": "T4 Cambridge",
        "address": "https://maps.app.goo.gl/dncTUZEio5haZtD69",
        "lastVisited": "",
        "comments": ""
    },
    {
        "lngLat": [-0.138824, 51.524166],
        "name": "T4 Warren Street",
        "address": "https://maps.app.goo.gl/CWSZM1PZnmzXeMNY9",
        "lastVisited": "2025-03-05",
        "comments": ""
    },
    {
        "lngLat": [-0.118778, 51.511304],
        "name": "T4 Strand",
        "address": "https://maps.app.goo.gl/eSrCgm4a64XpTwLw7",
        "lastVisited": "2024-03-27",
        "comments": ""
    },
    {
        "lngLat": [-0.086519, 51.526121],
        "name": "T4 Shoreditch",
        "address": "https://maps.app.goo.gl/SiMHk8oLvjp1cZqC9",
        "lastVisited": "2024-06-14",
        "comments": ""
    },
    {
        "lngLat": [-0.080886, 51.651895],
        "name": "T4 Enfield",
        "address": "https://maps.app.goo.gl/e7UD7595Gdfb6spw7",
        "lastVisited": "",
        "comments": ""
    },
    {
        "lngLat": [-0.111998, 51.501306],
        "name": "T4 Waterloo",
        "address": "https://maps.app.goo.gl/bjcFefZXmjhoy2eX8",
        "lastVisited": "don't remember",
        "comments": "but I do remember this was actually one of the few T4s that disappointed me :( maybe it was an off day"
    },
    {
        "lngLat": [-0.0750393, 51.516048],
        "name": "T4 Whitechapel",
        "address": "https://maps.app.goo.gl/eBwZeXwf8R6vZ7SUA",
        "lastVisited": "",
        "comments": ""
    },
    {
        "lngLat": [-0.419312, 51.505923],
        "name": "T4 Hayes",
        "address": "https://maps.app.goo.gl/gHz2Zx5ytU18gPmH6",
        "lastVisited": "",
        "comments": ""
    },
    {
        "lngLat": [-0.00971, 51.481194],
        "name": "T4 Greenwich",
        "address": "https://maps.app.goo.gl/eo3LrVnFnpqJVMYm7",
        "lastVisited": "sometime August 2024",
        "comments": ""
    },
    {
        "lngLat": [0.521504, 51.2732],
        "name": "T4 Maidstone",
        "address": "https://maps.app.goo.gl/fPzW7fhWeL41m1T58",
        "lastVisited": "",
        "comments": ""
    },
    {
        "lngLat": [-2.237781, 53.480271],
        "name": "T4 Manchester",
        "address": "https://maps.app.goo.gl/YhqWz4Zgc72ufKEm6",
        "lastVisited": "2025-08-14",
        "comments": "I also experienced a Manchester tram..."
    },
    {
        "lngLat": [-0.116905, 51.559067],
        "name": "T4 Seven Sisters",
        "address": "https://maps.app.goo.gl/rmZZjJC1Qi5xqvLK6",
        "lastVisited": "",
        "comments": ""
    },
    {
        "lngLat": [-1.576905, 54.776154],
        "name": "T4 Durham",
        "address": "https://maps.app.goo.gl/QJYXh4GYuX845HS18",
        "lastVisited": "",
        "comments": ""
    },
    {
        "lngLat": [0.016836, 51.399948],
        "name": "T4 Bromley",
        "address": "https://maps.app.goo.gl/c5Ne3BYMmtvdffrK7",
        "lastVisited": "",
        "comments": ""
    },
    {
        "lngLat": [-0.097931, 51.492214],
        "name": "T4 Elephant and Castle",
        "address": "https://maps.app.goo.gl/os7SRNgS78wUiLre6",
        "lastVisited": "",
        "comments": ""
    },
    {
        "lngLat": [-0.114300, 51.464928],
        "name": "T4 Brixton",
        "address": "https://maps.app.goo.gl/osXgMbztip8KHNAJ7",
        "lastVisited": "",
        "comments": ""
    },
    {
        "lngLat": [-0.023961, 51.584176],
        "name": "T4 Walthamstow",
        "address": "https://maps.app.goo.gl/majJG1fECTCpXZ6U7",
        "lastVisited": "2026-03-07",
        "comments": "The first time I came here I tried to order in Mandarin and the staff member had to tell me she didn't understand it. I was mortified! Since then I don't think I've ordered any bubble tea in Mandarin..."
    },
    {
        "lngLat": [-0.109275, 51.595855],
        "name": "T4 Wood Green",
        "address": "https://maps.app.goo.gl/mcinGsCQNLFKX9oP9",
        "lastVisited": "",
        "comments": ""
    },
    {
        "lngLat": [-0.075894, 51.545895],
        "name": "T4 Dalston",
        "address": "https://maps.app.goo.gl/GZq4FbQ5beqA67T79",
        "lastVisited": "",
        "comments": ""
    },
    {
        "lngLat": [-0.0587796, 51.5267598],
        "name": "T4 Bethnal Green",
        "address": "https://maps.app.goo.gl/6tnw7qpU2mhay9WM7",
        "lastVisited": "",
        "comments": ""
    },
    {
        "lngLat": [-0.2696676, 51.5072093],
        "name": "T4 Acton",
        "address": "https://maps.app.goo.gl/im4UqdTQZLvBXToUA",
        "lastVisited": "2025-03-08",
        "comments": "Used to be my local!"
    },
    {
        "lngLat": [-0.1678403, 51.4615558],
        "name": "T4 Clapham Junction",
        "address": "https://maps.app.goo.gl/1DkuHZgBukEQNrgK9",
        "lastVisited": "",
        "comments": ""
    },
    {
        "lngLat": [-0.0547702, 51.5494127],
        "name": "T4 Hackney",
        "address": "jttps://maps.app.goo.gl/VpWiFwpcHqBMq5HH8",
        "lastVisited": "2023-11-25",
        "comments": "Came here after a flat viewing in Clapton."
    },
    {
        "lngLat": [-0.123897, 51.524182],
        "name": "T4 Brunswick",
        "address": "https://maps.app.goo.gl/8G3PHY2nxNq9bEba7",
        "lastVisited": "2026-06-24",
        "comments": "Old office :("
    },
    {
        "lngLat": [-0.2517368, 51.5953116],
        "name": "T4 Colindale",
        "address": "https://maps.app.goo.gl/hZ2RGLmjULuWyPXV8",
        "lastVisited": "",
        "comments": ""
    },
    {
        "lngLat": [-0.747976, 52.041592],
        "name": "T4 Milton Keynes",
        "address": "https://maps.app.goo.gl/xyBdJMebBK9Fa3fGA",
        "lastVisited": "",
        "comments": ""
    },
    {
        "lngLat": [-1.469106, 53.3815884],
        "name": "T4 Sheffield",
        "address": "https://maps.app.goo.gl/n3esBobSykZusYEs6",
        "lastVisited": "",
        "comments": ""
    },
    {
        "lngLat": [-0.069856, 51.471678],
        "name": "T4 Peckham",
        "address": "https://maps.app.goo.gl/XCi5U6Dpf5VWo9qE9",
        "lastVisited": "",
        "comments": ""
    },
    {
        "lngLat": [-0.102265, 51.519923],
        "name": "T4 Farringdon",
        "address": "https://maps.app.goo.gl/dp17YsZd4ZzH9qAJA",
        "lastVisited": "don't remember but definitely have been",
        "comments": ""
    },
    {
        "lngLat": [-0.1444707, 51.4817856],
        "name": "T4 Battersea",
        "address": "https://maps.app.goo.gl/Hwr1bc7yainor65U9",
        "lastVisited": "August 2025",
        "comments": ""
    },
    {
        "lngLat": [-3.17518, 51.485326],
        "name": "T4 Cardiff",
        "address": "https://maps.app.goo.gl/bWDkHihk2BBYE4oY8",
        "lastVisited": "",
        "comments": ""
    },
    {
        "lngLat": [-0.1054908, 51.534378],
        "name": "T4 Angel",
        "address": "https://maps.app.goo.gl/pKsqoKCxNr2cpXjo9",
        "lastVisited": "",
        "comments": ""
    },
    {
        "lngLat": [0.028135, 51.462546],
        "name": "T4 Kidbrooke",
        "address": "https://maps.app.goo.gl/R7eNpq7Jgu82fuj3A",
        "lastVisited": "",
        "comments": ""
    },

    {
        "lngLat": [-0.230622, 51.492679],
        "name": "HEYTEA Hammersmith",
        "address": "https://maps.app.goo.gl/gqW6chtehomo1HSj8",
        "lastVisited": "some time in 2024",
        "comments": "A bit of a disappointment NGL"
    },
    {
        "lngLat": [-0.201791, 51.484725],
        "name": "Panda Cha Tea",
        "address": "https://maps.app.goo.gl/tqS2PHT2zhX1KviC9",
        "lastVisited": "2025-03-01",
        "comments": "I came here after sitting on sofas at the Darlings of Chelsea showroom in Parsons Green. I actually can't remember much! I think it was decent. I recall the staff being very friendly, which to be honest weirded me out a bit because I'm used to the very impersonal bubble tea shops!"
    },
    {
        "lngLat": [-0.194512, 51.480516],
        "name": "Chatime Fulham",
        "address": "https://maps.app.goo.gl/gF4aukdqHMu8fW9q6",
        "lastVisited": "2025-11-14",
        "comments": "Came here after visiting Coach House Pianos nearby with Marie. Chatime is generally fine (although I prefer T4). This seems to be shut now though..."
    },
    {
        "lngLat": [-0.194512, 51.480516],
        "name": "Jen Tea Liverpool Street",
        "address": "https://maps.app.goo.gl/wefARNjTzrjxs2DUA",
        "lastVisited": "2025-08-21",
        "comments": "Visited after doing the Summer Experience just next door. Honestly the shop looked decent but I don't think it was that good!"
    },
    {
        "lngLat": [-0.009041, 51.543203],
        "name": "NUTTEA Stratford",
        "address": "https://maps.app.goo.gl/EPi8q9rMwqb9BbTt9",
        "lastVisited": "2026-06-02",
        "comments": "I only came here for the first time because T4 in Westfield Stratford was being refurbished. Turns out it's actually really good! It's vegan so the milk is replaced with various nut-derived milks. The pearls are good and I like that the almond milk actually gives it more flavour than the usual. Definitely recommend."
    },
    {
        "lngLat": [-0.092881, 51.522772],
        "name": "Frozen River",
        "address": "https://maps.app.goo.gl/7gu9ZafZVt7d4mFV8",
        "lastVisited": "2026-06-22",
        "comments": "Wasn't really expecting too much but it was decent! It definitely does look a little bit run-down inside though..."
    },
    {
        "lngLat": [-0.131933, 51.512154],
        "name": "Milksha",
        "address": "https://maps.app.goo.gl/ubyBa5iGTDfTE39y8",
        "lastVisited": "2026-03-20",
        "comments": "This is actually one of my favourite bubble tea shops anywhere, and I pretty much only ever get this in Chinatown. (I went here based on a Reddit recommendation...) They have golden honey pearls which are really nice, the consistency is good, the tea is good. Only thing is that the pearls are a bit sweet so definitely reduce the sugar on the tea!"
    },
    {
        "lngLat": [-0.131443, 51.512479],
        "name": "CoCo Chinatown",
        "address": "https://maps.app.goo.gl/X7TmKzQwQStMdyFf6",
        "lastVisited": "several years ago",
        "comments": "This used to be my go-to in Chinatown, it was pretty good. It seems it's shut now though..."
    },

    {
        "lngLat": [-1.257834, 51.752411],
        "name": "T4 Oxford (closed)",
        "address": "https://maps.app.goo.gl/cPrJagSYVskLu9dJ7",
        "lastVisited": "Sometime Feb 2020",
        "comments": "Opened in Feb 2020 and promptly closed due to the pandemic :(. I guess I am one of the few people who can claim to have been here though!"
    },
    {
        "lngLat": [-1.260737, 51.754021],
        "name": "Chatime Oxford (closed)",
        "address": "https://maps.app.goo.gl/dvp392ktaayzLNaA7",
        "lastVisited": "many years ago",
        "comments": "This used to be the only decent bubble tea in Oxford for a long time!"
    },
    {
        "lngLat": [-1.258352, 51.751692],
        "name": "Yifang Oxford",
        "address": "https://maps.app.goo.gl/CXpuvwfLAvuuk5g8A",
        "lastVisited": "many years ago",
        "comments": "I didn't like the pearls — too small and not chewy... They used to be on Queen Street, where this pin is, but then moved to New Inn Hall Street which is where the Google Maps address is."
    },
    {
        "lngLat": [-1.256187, 51.751718],
        "name": "Formosan Tea Bar",
        "address": "https://maps.app.goo.gl/TgRhRN31p2P1qm326",
        "lastVisited": "many years ago",
        "comments": "Honestly a bit of a weird one. The tea itself was nice but I think it always felt too healthy! But also, my sugar intake has decreased over time (when I first came to the UK I used to get 75% sugar and nowadays I often get 0%) — so maybe now I might actually like it more?!"
    },
    {
        "lngLat": [-1.256151, 51.753041],
        "name": "Mooboo Oxford",
        "address": "https://maps.app.goo.gl/UsMGucpBJ8N65JCf6",
        "lastVisited": "many years ago",
        "comments": "Right opposite my college! I think I only went once or twice though."
    },
    {
        "lngLat": [-1.257348, 51.752551],
        "name": "Coba",
        "address": "https://maps.app.goo.gl/AfRvfpaun29TN1tq5",
        "lastVisited": "many years ago",
        "comments": "To be honest, I don't remember much about this one, but I don't really think it met my standards, which is probably why I don't remember it..."
    },
    {
        "lngLat": [-1.251717, 51.752847],
        "name": "Fantastea",
        "address": "https://maps.app.goo.gl/CvhVRZr2p9iSPyK1A",
        "lastVisited": "many years ago",
        "comments": "When they first opened I thought it was pretty decent, but I feel like the quality of the bubble tea went down over time."
    },
    {
        "lngLat": [-1.235164, 51.747119],
        "name": "IN CHA",
        "address": "https://maps.app.goo.gl/CvhVRZr2p9iSPyK1A",
        "lastVisited": "many years ago",
        "comments": "Was very hyped by some Asian people I knew... I think it was alright, roughly on par with T4 I'd say? But also I went very close to closing time so that may have affected the experience."
    },

    {
        "lngLat": [-1.541822, 53.796454],
        "name": "Half Sugar",
        "address": "https://maps.app.goo.gl/3XcvBtK183PYBFpE8",
        "lastVisited": "2024-08-03",
        "comments": "This was the last thing Kat and I did when I visited Leeds for the Summer Experience and stayed with her. The bubble tea here was legitimately really good! Would definitely go back."
    },
    {
        "lngLat": [-1.552136, 53.808442],
        "name": "IUTEA",
        "address": "https://maps.app.goo.gl/7ecwbSn4f8Jw4SNB6",
        "lastVisited": "2026-03-24",
        "comments": "Was with Kat and Nathan at the LIDA Careers Festival. The 4.9 rating on Google Maps made me think it would be good but actually it was a let down :("
    },
    {
        "lngLat": [-2.240290, 53.477851],
        "name": "OHAYO TEA",
        "address": "https://maps.app.goo.gl/J8UAQyN4yMRXM8LH6",
        "lastVisited": "2022-06-30",
        "comments": "Plus/minus a day — I was here for an NMRDG meeting. The shop was really packed but I don't think I was particularly impressed by the bubble tea!"
    },
    {
        "lngLat": [-3.191517, 55.952639],
        "name": "The Magic Cup",
        "address": "https://maps.app.goo.gl/8bDCsY5FdcpNcsM47",
        "lastVisited": "2025-08-27",
        "comments": "Met Martin S here and there weren't very many bubble tea options. It wasn't great (but then again I wasn't expecting much haha)."
    },
    {
        "lngLat": [-1.105417, 50.795560],
        "name": "Bubble Citea Portmsmouth",
        "address": "https://maps.app.goo.gl/ckjghuR1Mn6Gjugt7",
        "lastVisited": "2023-06-09",
        "comments": "Stopped by on the way to the Isle of Wight for Caitlin's wedding. In general I'm highly sceptical of the shops that aren't overtly Chinese and this was no exception :(. Additionally I made the mistake of giving them my mobile number and wouldn't stop getting SMS spam for quite a while afterwards... oh well."
    },
    {
        "lngLat": [-1.620677, 54.971942],
        "name": "Bubble Cha",
        "address": "https://maps.app.goo.gl/VVz9cDgDJdL44Q6YA",
        "lastVisited": "2024-09-06",
        "comments": "This was after RSECon 2024. I seem to recall it was quite good! But sadly I think I had Covid on that day so I didn't really get to enjoy it as much as I'd have liked :("
    },


    {
        "lngLat": [0.026041, 51.593385],
        "name": "Mooboo South Woodford",
        "address": "https://maps.app.goo.gl/de4Rm2pXkRQKQGU77",
        "lastVisited": "2026-05-18",
        "comments": "It's not bad — the pearls are decent but I feel like I could sense the milk powder! T4 is still better imo."
    }
]
